easy_timing/__init__.py
easy_timing/test.py
easy_timing/timers.py
easy_timing-1.0.0.dist-info/DESCRIPTION.rst
easy_timing-1.0.0.dist-info/METADATA
easy_timing-1.0.0.dist-info/RECORD
easy_timing-1.0.0.dist-info/WHEEL
easy_timing-1.0.0.dist-info/metadata.json
easy_timing-1.0.0.dist-info/top_level.txt
