Metadata-Version: 2.0
Name: easy-timing
Version: 1.0.0
Summary: easy-to-use context manager & decorator for timing Python code
Home-page: https://github.com/ebrush/easy_timing
Author: Samuel Brush
Author-email: s.e.brush1@gmail.com
License: UNKNOWN
